{
  "version": 1,
  "isRoot": true,
  "tools": {
    "paket": {
      "version": "8.0.3",
      "commands": [
        "paket"
      ],
      "rollForward": false
    },
    "fable": {
      "version": "4.18.0",
      "commands": [
        "fable"
      ],
      "rollForward": false
    },
    "telplin": {
      "version": "8.0.1",
      "commands": [
        "telplin"
      ],
      "rollForward": false
    },
    "fantomas": {
      "version": "6.1.1",
      "commands": [
        "fantomas"
      ],
      "rollForward": false
    }
  }
}